target_bigquery.py
target_bigquery-1.4.0.dist-info/DESCRIPTION.rst
target_bigquery-1.4.0.dist-info/METADATA
target_bigquery-1.4.0.dist-info/RECORD
target_bigquery-1.4.0.dist-info/WHEEL
target_bigquery-1.4.0.dist-info/entry_points.txt
target_bigquery-1.4.0.dist-info/metadata.json
target_bigquery-1.4.0.dist-info/top_level.txt
