Metadata-Version: 2.0
Name: target-bigquery
Version: 1.4.0
Summary: Singer.io target for writing data to Google BigQuery
Home-page: https://github.com/RealSelf/target-bigquery
Author: RealSelf Business Intelligence
Author-email: UNKNOWN
License: UNKNOWN
Platform: UNKNOWN
Classifier: Programming Language :: Python :: 3 :: Only
Requires-Dist: jsonschema (==2.6.0)
Requires-Dist: singer-python (>=1.5.0)
Requires-Dist: google-api-python-client (>=1.6.2)
Requires-Dist: google-cloud (>=0.34.0)
Requires-Dist: google-cloud-bigquery (>=1.9.0)
Requires-Dist: oauth2client
